enigma_ravenscroft/__init__.py
enigma_ravenscroft/main.py
enigma_ravenscroft-1.0.0.dist-info/METADATA
enigma_ravenscroft-1.0.0.dist-info/WHEEL
enigma_ravenscroft-1.0.0.dist-info/entry_points.txt
enigma_ravenscroft-1.0.0.dist-info/top_level.txt
enigma_ravenscroft-1.0.0.dist-info/RECORD
